cpp_package_for_python.cpython-38-x86_64-linux-gnu.so
cpp_package_for_python-0.0.2.dist-info/LICENSE.txt
cpp_package_for_python-0.0.2.dist-info/METADATA
cpp_package_for_python-0.0.2.dist-info/WHEEL
cpp_package_for_python-0.0.2.dist-info/top_level.txt
cpp_package_for_python-0.0.2.dist-info/RECORD
